{
  "swagger": "2.0",
  "info": {
    "title": "api/v1/operations.proto",
    "version": "version not set"
  },
  "tags": [
    {
      "name": "OperationsService"
    }
  ],
  "consumes": [
    "application/json"
  ],
  "produces": [
    "application/json"
  ],
  "paths": {
    "/schedulers/{schedulerName}/operations": {
      "get": {
        "summary": "List operations based on a scheduler.",
        "operationId": "OperationsService_ListOperations",
        "responses": {
          "200": {
            "description": "A successful response.",
            "schema": {
              "$ref": "#/definitions/v1ListOperationsResponse"
            }
          },
          "default": {
            "description": "An unexpected error response.",
            "schema": {
              "$ref": "#/definitions/rpcStatus"
            }
          }
        },
        "parameters": [
          {
            "name": "schedulerName",
            "description": "Scheduler name that the operations are part of.\nNOTE: On http protocol, this operates as a path param.",
            "in": "path",
            "required": true,
            "type": "string"
          },
          {
            "name": "orderBy",
            "description": "Optional parameter for enabling operations sorting.\nGeneral `order_by` string syntax: \u003cfield\u003e (\u003casc|desc\u003e)\nNOTE: On http protocol, this operates as a query parameter.",
            "in": "query",
            "required": false,
            "type": "string"
          }
        ],
        "tags": [
          "OperationsService"
        ]
      }
    },
    "/schedulers/{schedulerName}/operations/{operationId}/cancel": {
      "post": {
        "summary": "Cancel operation based on scheduler name and operation ID",
        "operationId": "OperationsService_CancelOperation",
        "responses": {
          "200": {
            "description": "A successful response.",
            "schema": {
              "$ref": "#/definitions/v1CancelOperationResponse"
            }
          },
          "default": {
            "description": "An unexpected error response.",
            "schema": {
              "$ref": "#/definitions/rpcStatus"
            }
          }
        },
        "parameters": [
          {
            "name": "schedulerName",
            "description": "Scheduler name where the operation relies on.",
            "in": "path",
            "required": true,
            "type": "string"
          },
          {
            "name": "operationId",
            "description": "Operation identifier to be canceled.",
            "in": "path",
            "required": true,
            "type": "string"
          }
        ],
        "tags": [
          "OperationsService"
        ]
      }
    }
  },
  "definitions": {
    "protobufAny": {
      "type": "object",
      "properties": {
        "typeUrl": {
          "type": "string"
        },
        "value": {
          "type": "string",
          "format": "byte"
        }
      }
    },
    "rpcStatus": {
      "type": "object",
      "properties": {
        "code": {
          "type": "integer",
          "format": "int32"
        },
        "message": {
          "type": "string"
        },
        "details": {
          "type": "array",
          "items": {
            "$ref": "#/definitions/protobufAny"
          }
        }
      }
    },
    "v1CancelOperationResponse": {
      "type": "object",
      "description": "Empty response of the cancel operation request."
    },
    "v1ListOperationsResponse": {
      "type": "object",
      "properties": {
        "pendingOperations": {
          "type": "array",
          "items": {
            "$ref": "#/definitions/v1Operation"
          },
          "description": "List of the scheduler pending operations."
        },
        "activeOperations": {
          "type": "array",
          "items": {
            "$ref": "#/definitions/v1Operation"
          },
          "description": "List of the scheduler active operations."
        },
        "finishedOperations": {
          "type": "array",
          "items": {
            "$ref": "#/definitions/v1Operation"
          },
          "description": "List of the scheduler finished (with error or not) operations."
        }
      },
      "title": "The list operation route response/reply\nThere's a list for each operation major status"
    },
    "v1Operation": {
      "type": "object",
      "properties": {
        "id": {
          "type": "string",
          "description": "Unique identifier for the operation."
        },
        "status": {
          "type": "string",
          "description": "Current status of the operation.\nTODO(gabrielcorado): change to enum."
        },
        "definitionName": {
          "type": "string",
          "description": "Name of the operation being executed."
        },
        "schedulerName": {
          "type": "string",
          "description": "Scheduler indentifier that the operation is from."
        },
        "createdAt": {
          "type": "string",
          "format": "date-time",
          "description": "Time the operation was created."
        }
      },
      "title": "The operation object representation"
    }
  }
}
